denograd.py
denograd-1.0.0.dist-info/licenses/LICENSE
denograd-1.0.0.dist-info/METADATA
denograd-1.0.0.dist-info/WHEEL
denograd-1.0.0.dist-info/top_level.txt
denograd-1.0.0.dist-info/RECORD
